flask_apispec_tools/__init__.py
flask_apispec_tools/commands.py
flask_apispec_tools/endpoints.py
flask_apispec_tools/tools.py
flask_apispec_tools/templates/__init__.py
flask_apispec_tools/templates/swagger-ui.html
flask_apispec_tools-0.2.0.dist-info/LICENSE
flask_apispec_tools-0.2.0.dist-info/METADATA
flask_apispec_tools-0.2.0.dist-info/WHEEL
flask_apispec_tools-0.2.0.dist-info/top_level.txt
flask_apispec_tools-0.2.0.dist-info/RECORD
