Metadata-Version: 2.1
Name: flask-apispec-tools
Version: 0.2.0
Summary: A set of tools to aid in adding APISpec to Flask projects.
Author: Mike Brady
License: MIT License
Project-URL: homepage, https://github.com/mike-brady/flask-apispec-tools
Project-URL: repository, https://github.com/mike-brady/flask-apispec-tools
License-File: LICENSE
Requires-Dist: apispec-webframeworks ; python_version >= "0.5.2"
Requires-Dist: Flask ; python_version >= "2.2.3"
Requires-Dist: apispec ; python_version >= "6.3.0"
